Metadata-Version: 2.1
Name: seglines
Version: 0.0.5
Summary: Segmented Least Squares
Home-page: https://github.com/pgdr/seglines
Author: PG Drange
Author-email: Pal.Drange@uib.no
Maintainer: PG Drange <Pal.Drange@uib.no>
License: MIT
Project-URL: Bug Tracker, https://github.com/pgdr/seglines/issues
Project-URL: Documentation, https://github.com/pgdr/seglines/blob/master/README.md
Project-URL: Source Code, https://github.com/pgdr/seglines
Keywords: seglines
